QueryStringManager/QueryStringManager.py
QueryStringManager/__init__.py
Query_String_Manager-1.0.11.dist-info/LICENSE
Query_String_Manager-1.0.11.dist-info/METADATA
Query_String_Manager-1.0.11.dist-info/WHEEL
Query_String_Manager-1.0.11.dist-info/top_level.txt
Query_String_Manager-1.0.11.dist-info/RECORD
